avalonia/net6.0/Avalonia.Base.dll
avalonia/net6.0/Avalonia.Base.xml
avalonia/net6.0/Avalonia.Controls.dll
avalonia/net6.0/Avalonia.Controls.xml
avalonia/net6.0/Avalonia.DesignerSupport.dll
avalonia/net6.0/Avalonia.DesignerSupport.xml
avalonia/net6.0/Avalonia.Dialogs.dll
avalonia/net6.0/Avalonia.Dialogs.xml
avalonia/net6.0/Avalonia.dll
avalonia/net6.0/Avalonia.Markup.dll
avalonia/net6.0/Avalonia.Markup.Xaml.dll
avalonia/net6.0/Avalonia.Markup.Xaml.xml
avalonia/net6.0/Avalonia.Markup.xml
avalonia/net6.0/Avalonia.Metal.dll
avalonia/net6.0/Avalonia.Metal.xml
avalonia/net6.0/Avalonia.MicroCom.dll
avalonia/net6.0/Avalonia.MicroCom.xml
avalonia/net6.0/Avalonia.OpenGL.dll
avalonia/net6.0/Avalonia.OpenGL.xml
avalonia/net6.0/Avalonia.xml
avalonia/net60.py
avalonia_net60-0.1.0.dist-info/METADATA
avalonia_net60-0.1.0.dist-info/WHEEL
avalonia_net60-0.1.0.dist-info/RECORD
